CHANGELOG.txt
LICENSE.txt
MANIFEST.in
README.txt
setup.py
supsubscript/__init__.py
supsubscript.egg-info/PKG-INFO
supsubscript.egg-info/SOURCES.txt
supsubscript.egg-info/dependency_links.txt
supsubscript.egg-info/top_level.txt